Workbook

Sheet Assumptions
A1: Trade Settlement Failure Risk Model
A3: Lifecycle Stage | B3: What Can Go Wrong Here | C3: Failure Probaility | D3: Sources
A5: Trade Capture / Execution | B5: data entry error on trade details | C5: 0.0004 | D5: No public per-stage data available thin residual allocation of the unexplained ~3% of fails, not independently sourced.
A6: Trade Validation | B6: incomplete or inaccurate trade details, missing static/reference data, counterparty limit breach | C6: 0.0004 | D6: No public per-stage data available thin residual allocation of the unexplained ~3% of fails, not independently sourced.
A7: Trade Confirmation | B7: buyer/seller trade details don't match | C7: 0.0162 | D7: Weighted from ERCC cause breakdown 27% of fails attributed to instruction matching errors and applied to ESMA's 6% EU equity fail rate (Dec 2022).
A8: Clearing (CCP Novation) | B8: trade fails to clear through the CCP | C8: 0.0004 | D8: No public per-stage data available thin residual allocation of the unexplained ~3% of fails, not independently sourced.
A9: Settlement Instruction (SSI) Matching | B9: settlement instructions mismatch between parties | C9: 0.0004 | D9: No public per-stage data available thin residual allocation of the unexplained ~3% of fails, not independently sourced.
A10: Settlement (Delivery vs Payment) | B10: insufficient securities or cash on settlement date | C10: 0.042 | D10: Weighted from ERCC cause breakdown 70% of fails attributed to sellers unable to deliver securities applied to ESMA's 6% EU equity fail rate (Dec 2022).
A11: Post-Settlement Reconciliation | B11: break found between internal books and custodian records | C11: 0.0004 | D11: No public per-stage data available thin residual allocation of the unexplained ~3% of fails, not independently sourced.
A13: Overall probability of clean settlement | C13: =(1-C5)*(1-C6)*(1-C7)*(1-CC58)*(1-C9)*(1-C10)*(1-C11) -> 0.94097334
A14: Overall probability of failure (per trade) | C14: =(1-C13) -> 0.059026664
A16: Methodology note: Confirmation/Matching and Settlement (DvP) probabilities are derived from ERCC's published cause breakdown (matching errors 27%, delivery failures 70%) applied to ESMA's 6% EU equity settlement fail rate (Dec 2022). Remaining stages use a thin equal-split residual due to lack of public per-stage data.

Sheet Model
A1: Batch-Level Failure Model
A4: Batch Size- No. Of Trades | B4: 20000
A5: Failure Probability | B5: =Assumptions!C14 -> 0.059026664
A6: Failed Trades | B6: =B5*B4 -> 1180.5333
A7: Standard Dev. Of Failures | B7: =SQRT(B4*B5*(1-B5)) -> 33.329422
A9: Probability of exactly k failed trades in the batch
A10: Failed Trades(k) | B10: Probabilty of Failed Trades P(exactly k) | C10: Cumulative P(<=k)
A11: =B6-3*B7 -> 1080.545 | B11: =BINOMDIST(A11,B4,B5, FALSE) -> 0.00011630448 | C11: =BINOMDIST(A11,B4,B5,TRUE) -> 0.0011904042
A12: =B6-2*B7 -> 1113.8744 | B12: =BINOMDIST(A12,B4,B5,FALSE) -> 0.0015209981 | C12: =BINOMDIST(A12,B4,B5,TRUE) -> 0.021430688
A13: =B6-B7 -> 1147.2039 | B13: =BINOMDIST(A13,B4,B5,FALSE) -> 0.0072799887 | C13: =BINOMDIST(A13,B4,B5,TRUE) -> 0.16082697
A14: =B6 -> 1180.5333 | B14: =BINOMDIST(A14,B4,B5,FALSE) -> 0.011969827 | C14: =BINOMDIST(A14,B4,B5,TRUE) -> 0.50136125
A15: =B6+B7 -> 1213.8627 | B15: =BINOMDIST(A15,B4,B5,FALSE) -> 0.007382968 | C15: =BINOMDIST(A15,B4,B5,TRUE) -> 0.83872732
A16: =B6+2*B7 -> 1247.1921 | B16: =BINOMDIST(A16,B4,B5,FALSE) -> 0.0016523927 | C16: =BINOMDIST(A16,B4,B5,TRUE) -> 0.9770446
A17: =B6+3*B7 -> 1280.5215 | B17: =BINOMDIST(A17,B4,B5,FALSE) -> 0.00015014365 | C17: =BINOMDIST(A17,B4,B5,TRUE) -> 0.99848846
A18: =B6+4*B7 -> 1313.851 | B18: =BINOMDIST(A18,B4,B5,FALSE) -> 5.4985844e-06 | C18: =BINOMDIST(A18,B4,B5,TRUE) -> 0.99995695
A19: =B6+5*B7 -> 1347.1804 | B19: =BINOMDIST(A19,B4,B5,FALSE) -> 7.2020816e-08 | C19: =BINOMDIST(A19,B4,B5,TRUE) -> 0.99999954

Sheet Cost Impact
A1: Cost Impact sheet
A3: Average Trade Value(₹) | B3: 5000000
A4: Fail Fee% | B4: 0.001
A5: Fee Floor(₹) | B5: 4000
A6: Fee Cap(₹) | B6: 150000
A7: Funding Cost Per Fail(₹) | B7: 600
A8: Operation Cost Per Fail(₹) | B8: 1400
A10: Fee cost per failed trade (floor/cap applied) | B10: =MAX(B5,MIN(B4*B3,B6)) -> 5000
A11: Total cost per single failed trade | B11: =B10+B7+B8 -> 7000
A13: Expected Number Of Failed Trades | B13: =Model!B6 -> 1180.5333
A14: Expected Cost Per Batch | B14: =B13*B11 -> 8263733
A17: Cost figures on this sheet are self estimated, illustrative assumptions not real bank data, since per trade cost figures are internal and not publicly disclosed. The goal is to demonstrate the methodology for converting failure probability into expected cost, not to produce an audited real world estimate.

Sheet Sensitivity
A1: Sensitivity Analysis
A3: Life Cycle Stage | B3: Base Probability | C3: LOW(~50) | D3: HIGH(~50) | E3: Overall Fail LOW | F3: Overall Fail HIGH | G3: Swing(High -Low) | H3: Cost Swing | I3: Savings From Halving
A4: =Assumptions!A5 -> Trade Capture / Execution | B4: =Assumptions!C5 -> 0.0004 | C4: =B4*0.5 -> 0.0002 | D4: =B4*1.5 -> 0.0006 | E4: =1-((Assumptions!C13)*(1-C4)/(1-B4)) -> 0.058838394 | F4: =1-((Assumptions!C13)*(1-D4)/(1-B4)) -> 0.059214934 | G4: =F4-E4 -> 0.00037653995 | H4: =G4*Model!B4*'Cost Impact'!B11 -> 52715.593 | I4: =(Assumptions!C14 - E4)*Model!B4*'Cost Impact'!B11 -> 26357.797
A5: =Assumptions!A6 -> Trade Validation | B5: =Assumptions!C6 -> 0.0004 | C5: =B5*0.5 -> 0.0002 | D5: =B5*1.5 -> 0.0006 | E5: =1-((Assumptions!C13)*(1-C5)/(1-B5)) -> 0.058838394 | F5: =1-((Assumptions!C13)*(1-D5)/(1-B5)) -> 0.059214934 | G5: =F5-E5 -> 0.00037653995 | H5: =G5*Model!B4*'Cost Impact'!B11 -> 52715.593 | I5: =(Assumptions!C14 - E5)*Model!B4*'Cost Impact'!B11 -> 26357.797
A6: =Assumptions!A7 -> Trade Confirmation | B6: =Assumptions!C7 -> 0.0162 | C6: =B6*0.5 -> 0.0081 | D6: =B6*1.5 -> 0.0243 | E6: =1-((Assumptions!C13)*(1-C6)/(1-B6)) -> 0.051279272 | F6: =1-((Assumptions!C13)*(1-D6)/(1-B6)) -> 0.066774056 | G6: =F6-E6 -> 0.015494784 | H6: =G6*Model!B4*'Cost Impact'!B11 -> 2169269.7 | I6: =(Assumptions!C14 - E6)*Model!B4*'Cost Impact'!B11 -> 1084634.8
A7: =Assumptions!A8 -> Clearing (CCP Novation) | B7: =Assumptions!C8 -> 0.0004 | C7: =B7*0.5 -> 0.0002 | D7: =B7*1.5 -> 0.0006 | E7: =1-((Assumptions!C13)*(1-C7)/(1-B7)) -> 0.058838394 | F7: =1-((Assumptions!C13)*(1-D7)/(1-B7)) -> 0.059214934 | G7: =F7-E7 -> 0.00037653995 | H7: =G7*Model!B4*'Cost Impact'!B11 -> 52715.593 | I7: =(Assumptions!C14 - E7)*Model!B4*'Cost Impact'!B11 -> 26357.797
A8: =Assumptions!A9 -> Settlement Instruction (SSI) Matching | B8: =Assumptions!C9 -> 0.0004 | C8: =B8*0.5 -> 0.0002 | D8: =B8*1.5 -> 0.0006 | E8: =1-((Assumptions!C13)*(1-C8)/(1-B8)) -> 0.058838394 | F8: =1-((Assumptions!C13)*(1-D8)/(1-B8)) -> 0.059214934 | G8: =F8-E8 -> 0.00037653995 | H8: =G8*Model!B4*'Cost Impact'!B11 -> 52715.593 | I8: =(Assumptions!C14 - E8)*Model!B4*'Cost Impact'!B11 -> 26357.797
A9: =Assumptions!A10 -> Settlement (Delivery vs Payment) | B9: =Assumptions!C10 -> 0.042 | C9: =B9*0.5 -> 0.021 | D9: =B9*1.5 -> 0.063 | E9: =1-((Assumptions!C13)*(1-C9)/(1-B9)) -> 0.0383999 | F9: =1-((Assumptions!C13)*(1-D9)/(1-B9)) -> 0.079653428 | G9: =F9-E9 -> 0.041253528 | H9: =G9*Model!B4*'Cost Impact'!B11 -> 5775494 | I9: =(Assumptions!C14 - E9)*Model!B4*'Cost Impact'!B11 -> 2887747
A10: =Assumptions!A11 -> Post-Settlement Reconciliation | B10: =Assumptions!C11 -> 0.0004 | C10: =B10*0.5 -> 0.0002 | D10: =B10*1.5 -> 0.0006 | E10: =1-((Assumptions!C13)*(1-C10)/(1-B10)) -> 0.058838394 | F10: =1-((Assumptions!C13)*(1-D10)/(1-B10)) -> 0.059214934 | G10: =F10-E10 -> 0.00037653995 | H10: =G10*Model!B4*'Cost Impact'!B11 -> 52715.593 | I10: =(Assumptions!C14 - E10)*Model!B4*'Cost Impact'!B11 -> 26357.797
A13: Settlement (Delivery vs Payment) is the highest leverage stage halving its failure rate alone would save roughly ₹28.8 lakh in expected daily batch cost, the largest single stage improvement in the model.

Sheet Dashboard
A1: DASHBOARD
A3: Overall failure probability | B3: =Assumptions!C14 -> 0.059026664
A4: Batch size | B4: =Model!B4 -> 20000
A5: Expected failed trades | B5: =Model!B6 -> 1180.5333
A6: Expected cost per batch | B6: ='Cost Impact'!B14 -> 8263733
A7: Highest-leverage stage | B7: =INDEX(Sensitivity!A4:A10, MATCH(MAX(Sensitivity!H4:H10),Sensitivity!H4:H10,0)) -> Settlement (Delivery vs Payment)
A8: Savings From Halving | B8: =INDEX(Sensitivity!I4:I10, MATCH(MAX(Sensitivity!H4:H10),Sensitivity!H4:H10,0)) -> 2887747
A10: ="Recommendation: Focus on " & B7 & " halving its failure rate would save approximately ₹" & TEXT(B8,"#,##0") & " per batch." -> Recommendation: Focus on Settlement (Delivery vs Payment) halving its failure rate would save approximately ₹2,887,747 per batch.
